milkpay/xrocket/__init__.py
milkpay/xrocket/__meta__.py
milkpay/xrocket/py.typed
milkpay/xrocket/enums/__init__.py
milkpay/xrocket/enums/cheque_status.py
milkpay/xrocket/enums/invoice_status.py
milkpay/xrocket/enums/network_code.py
milkpay/xrocket/enums/order_execute_type.py
milkpay/xrocket/enums/order_status.py
milkpay/xrocket/enums/order_type.py
milkpay/xrocket/enums/subscription_interval.py
milkpay/xrocket/enums/subscription_status.py
milkpay/xrocket/enums/webhook_type.py
milkpay/xrocket/enums/withdrawal_status.py
milkpay/xrocket/pay/__init__.py
milkpay/xrocket/pay/client.py
milkpay/xrocket/pay/exceptions.py
milkpay/xrocket/pay/methods/__init__.py
milkpay/xrocket/pay/methods/base.py
milkpay/xrocket/pay/methods/check_subscription.py
milkpay/xrocket/pay/methods/create_cheque.py
milkpay/xrocket/pay/methods/create_invoice.py
milkpay/xrocket/pay/methods/create_subscription.py
milkpay/xrocket/pay/methods/create_subscription_interval.py
milkpay/xrocket/pay/methods/delete_cheque.py
milkpay/xrocket/pay/methods/delete_invoice.py
milkpay/xrocket/pay/methods/delete_subscription.py
milkpay/xrocket/pay/methods/delete_subscription_interval.py
milkpay/xrocket/pay/methods/edit_cheque.py
milkpay/xrocket/pay/methods/edit_subscription_interval.py
milkpay/xrocket/pay/methods/get_app_info.py
milkpay/xrocket/pay/methods/get_cheque.py
milkpay/xrocket/pay/methods/get_cheques.py
milkpay/xrocket/pay/methods/get_coins.py
milkpay/xrocket/pay/methods/get_invoice.py
milkpay/xrocket/pay/methods/get_invoices.py
milkpay/xrocket/pay/methods/get_subscription.py
milkpay/xrocket/pay/methods/get_subscription_interval.py
milkpay/xrocket/pay/methods/get_subscriptions.py
milkpay/xrocket/pay/methods/get_version.py
milkpay/xrocket/pay/methods/get_withdrawal_fees.py
milkpay/xrocket/pay/methods/get_withdrawal_status.py
milkpay/xrocket/pay/methods/transfer.py
milkpay/xrocket/pay/methods/withdrawal.py
milkpay/xrocket/pay/types/__init__.py
milkpay/xrocket/pay/types/api_bad_request_error.py
milkpay_xrocket-1.0.1.dist-info/METADATA
milkpay_xrocket-1.0.1.dist-info/WHEEL
milkpay_xrocket-1.0.1.dist-info/licenses/LICENSE
milkpay_xrocket-1.0.1.dist-info/RECORD
